package_python_function/__init__.py
package_python_function/main.py
package_python_function/nested_zip_loader.py
package_python_function/packager.py
package_python_function/python_project.py
package_python_function/reproducible_zipfile.py
package_python_function-0.0.11.dist-info/LICENSE
package_python_function-0.0.11.dist-info/METADATA
package_python_function-0.0.11.dist-info/WHEEL
package_python_function-0.0.11.dist-info/entry_points.txt
package_python_function-0.0.11.dist-info/RECORD
