Metadata-Version: 2.3
Name: package-python-function
Version: 0.0.11
Summary: Python script to package a Python function for deploying to AWS Lambda
License: MIT
Author: Brandon White
Author-email: brandonlwhite@gmail.com
Requires-Python: >=3.10,<4.0
Classifier: License :: OSI Approved :: MIT License
Classifier: Programming Language :: Python :: 3
Classifier: Programming Language :: Python :: 3.10
Classifier: Programming Language :: Python :: 3.11
Classifier: Programming Language :: Python :: 3.12
Classifier: Programming Language :: Python :: 3.13
Project-URL: Repository, https://github.com/BrandonLWhite/package-python-function
